song_organizer/__init__.py
song_organizer/__main__.py
song_organizer/organizer.py
nyonge-0.1.0.dist-info/LICENSE
nyonge-0.1.0.dist-info/METADATA
nyonge-0.1.0.dist-info/WHEEL
nyonge-0.1.0.dist-info/entry_points.txt
nyonge-0.1.0.dist-info/top_level.txt
nyonge-0.1.0.dist-info/RECORD
